jaxmod/__init__.py
jaxmod/constants.py
jaxmod/solvers.py
jaxmod/type_aliases.py
jaxmod/units.py
jaxmod/utils.py
jaxmod-0.4.0.dist-info/METADATA
jaxmod-0.4.0.dist-info/WHEEL
jaxmod-0.4.0.dist-info/licenses/LICENSE
jaxmod-0.4.0.dist-info/RECORD
